<doxygenlayout version="1.0">
  <!-- Generated by doxygen 1.8.4 -->
  <!-- Navigation index tabs for HTML output -->
  <navindex>
    <tab type="mainpage" visible="yes" title=""/>
    <tab type="pages" visible="yes" title="" intro=""/>
    <tab type="modules" visible="yes" title="Testing" intro=""/>
    <tab type="namespaces" visible="yes" title="Testxzyw">
      <tab type="namespacelist" visible="yes" title="Testabc" intro=""/>
      <tab type="namespacemembers" visible="yes" title="Testabcd" intro=""/>
    </tab>
    <tab type="classes" visible="yes" title="Modules">
      <tab type="classlist" visible="yes" title="Module list" intro="All structures, signatures and functors are listed here."/>
      <tab type="classindex" visible="$ALPHABETICAL_INDEX" title="Module index"/>
      <tab type="hierarchy" visible="yes" title="Module hierarchy" intro="This list of structures, signatures and functors is sorted roughly, but not completely, alphabetically."/>
      <tab type="classmembers" visible="yes" title="Module members" intro="Here is a list of all the documented module members with links to the module documentation for each member."/>
    </tab>
    <tab type="files" visible="yes" title="">
      <tab type="filelist" visible="yes" title="" intro=""/>
      <tab type="globals" visible="yes" title="" intro=""/>
    </tab>
    <tab type="examples" visible="yes" title="" intro=""/>
  </navindex>

  <!-- Layout definition for a class page -->
  <class>
    <briefdescription visible="yes" title="testblah">
    <includes visible="$SHOW_INCLUDE_FILES"/>
    <inheritancegraph visible="$CLASS_GRAPH"/>
    <collaborationgraph visible="$COLLABORATION_GRAPH"/>
    <detaileddescription title=""/>
    <memberdecl>
      <nestedclasses visible="yes" title=""/>
      <publictypes title=""/>
      <services title=""/>
      <interfaces title=""/>
      <publicslots title=""/>
      <signals title=""/>
      <publicmethods title=""/>
      <publicstaticmethods title=""/>
      <publicattributes title="Test3"/>
      <publicstaticattributes title="Value declarations"/>
      <protectedtypes title="Test2"/>
      <protectedslots title="Test4"/>
      <protectedmethods title="Test5"/>
      <protectedstaticmethods title="Test7"/>
      <protectedattributes title="Test6"/>
      <protectedstaticattributes title="Type and Datatype declarations"/>
      <packagetypes title="Test13"/>
      <packagemethods title="Test14"/>
      <packagestaticmethods title="Test15"/>
      <packageattributes title="Test16"/>
      <packagestaticattributes title="Test17"/>
      <properties title="Test18"/>
      <events title="Test19"/>
      <privatetypes title="Test11"/>
      <privateslots title="Test"/>
      <privatemethods title="Test"/>
      <privatestaticmethods title=""/>
      <privateattributes title=""/>
      <privatestaticattributes title=""/>
      <friends title=""/>
      <related title="" subtitle=""/>
      <membergroups visible="yes"/>
    </memberdecl>
    <memberdef>
      <inlineclasses title="Test90"/>
      <typedefs title="Test91"/>
      <enums title="Test92"/>
      <services title="Test93"/>
      <interfaces title="Test94"/>
      <constructors title="Test95"/>
      <functions title="Member function documentation"/>
      <related title="Test96"/>
      <variables title="Type and Datatype declarations"/>
      <properties title="Test98"/>
      <events title="Test99"/>
    </memberdef>
    <allmemberslink visible="yes"/>
    <usedfiles visible="$SHOW_USED_FILES"/>
    <authorsection visible="yes"/>
  </class>

  <!-- Layout definition for a namespace page -->
  <namespace>
    <briefdescription visible="yes"/>
    <memberdecl>
      <nestednamespaces visible="yes" title=""/>
      <constantgroups visible="yes" title=""/>
      <classes visible="yes" title="Modules"/>
      <typedefs title=""/>
      <enums title=""/>
      <functions title=""/>
      <variables title=""/>
      <membergroups visible="yes"/>
    </memberdecl>
    <detaileddescription title=""/>
    <memberdef>
      <inlineclasses title=""/>
      <typedefs title=""/>
      <enums title=""/>
      <functions title=""/>
      <variables title=""/>
    </memberdef>
    <authorsection visible="yes"/>
  </namespace>

  <!-- Layout definition for a file page -->
  <file>
    <briefdescription visible="yes"/>
    <includes visible="$SHOW_INCLUDE_FILES"/>
    <includegraph visible="$INCLUDE_GRAPH"/>
    <includedbygraph visible="$INCLUDED_BY_GRAPH"/>
    <sourcelink visible="yes"/>
    <memberdecl>
      <classes visible="yes" title="Test"/>
      <namespaces visible="yes" title=""/>
      <constantgroups visible="yes" title=""/>
      <defines title=""/>
      <typedefs title=""/>
      <enums title=""/>
      <functions title=""/>
      <variables title=""/>
      <membergroups visible="yes"/>
    </memberdecl>
    <detaileddescription title=""/>
    <memberdef>
      <inlineclasses title=""/>
      <defines title=""/>
      <typedefs title=""/>
      <enums title=""/>
      <functions title=""/>
      <variables title=""/>
    </memberdef>
    <authorsection/>
  </file>

  <!-- Layout definition for a group page -->
  <group>
    <briefdescription visible="yes"/>
    <groupgraph visible="$GROUP_GRAPHS"/>
    <memberdecl>
      <nestedgroups visible="yes" title=""/>
      <dirs visible="yes" title=""/>
      <files visible="yes" title=""/>
      <namespaces visible="yes" title=""/>
      <classes visible="yes" title="Test"/>
      <defines title=""/>
      <typedefs title=""/>
      <enums title=""/>
      <enumvalues title=""/>
      <functions title=""/>
      <variables title=""/>
      <signals title=""/>
      <publicslots title=""/>
      <protectedslots title=""/>
      <privateslots title=""/>
      <events title=""/>
      <properties title=""/>
      <friends title=""/>
      <membergroups visible="yes"/>
    </memberdecl>
    <detaileddescription title=""/>
    <memberdef>
      <pagedocs/>
      <inlineclasses title=""/>
      <defines title=""/>
      <typedefs title=""/>
      <enums title=""/>
      <enumvalues title=""/>
      <functions title=""/>
      <variables title=""/>
      <signals title=""/>
      <publicslots title=""/>
      <protectedslots title=""/>
      <privateslots title=""/>
      <events title=""/>
      <properties title=""/>
      <friends title=""/>
    </memberdef>
    <authorsection visible="yes"/>
  </group>

  <!-- Layout definition for a directory page -->
  <directory>
    <briefdescription visible="yes"/>
    <directorygraph visible="yes"/>
    <memberdecl>
      <dirs visible="yes"/>
      <files visible="yes"/>
    </memberdecl>
    <detaileddescription title=""/>
  </directory>
</doxygenlayout>
